AUTHORS.rst
CONTRIBUTING.rst
HISTORY.rst
LICENSE
MANIFEST.in
README.rst
setup.cfg
setup.py
bin/stats
docs/Makefile
docs/authors.rst
docs/conf.py
docs/contributing.rst
docs/history.rst
docs/index.rst
docs/installation.rst
docs/make.bat
docs/modules.rst
docs/readme.rst
docs/sportsstats.rst
docs/usage.rst
lib/sportsstats/__init__.py
lib/sportsstats/utils.py
lib/sportsstats.egg-info/PKG-INFO
lib/sportsstats.egg-info/SOURCES.txt
lib/sportsstats.egg-info/dependency_links.txt
lib/sportsstats.egg-info/not-zip-safe
lib/sportsstats.egg-info/top_level.txt
lib/sportsstats/nba/__init__.py
lib/sportsstats/nba/downloader.py
tests/__init__.py
tests/test_nba.py