Metadata-Version: 1.1
Name: sportsstats
Version: 0.1.3
Summary: Tools for downloading sports statistics.
Home-page: https://github.com/mwilliammyers/sportsstats
Author: William Myers
Author-email: mwilliammyers+pypi@gmail.com
License: GPLv3+
Keywords: sportsstats stats statistics sports
Platform: UNKNOWN
Classifier: Development Status :: 2 - Pre-Alpha
Classifier: Intended Audience :: Developers
Classifier: License :: OSI Approved :: GNU General Public License v3 or later (GPLv3+)
Classifier: Natural Language :: English
Classifier: Programming Language :: Python :: 2
Classifier: Programming Language :: Python :: 2.6
Classifier: Programming Language :: Python :: 2.7
Classifier: Programming Language :: Python :: 3
Classifier: Programming Language :: Python :: 3.3
Classifier: Programming Language :: Python :: 3.4
Classifier: Programming Language :: Python :: 3.5
